server.py
bach_lunar_mcp-1.0.0.dist-info/licenses/LICENSE
tools/__init__.py
utils/__init__.py
utils/lunar_helper.py
bach_lunar_mcp-1.0.0.dist-info/METADATA
bach_lunar_mcp-1.0.0.dist-info/WHEEL
bach_lunar_mcp-1.0.0.dist-info/entry_points.txt
bach_lunar_mcp-1.0.0.dist-info/top_level.txt
bach_lunar_mcp-1.0.0.dist-info/RECORD
