Metadata-Version: 2.4
Name: bach-lunar-mcp
Version: 1.0.0
Summary: Chinese Lunar Calendar MCP Agent
Author-email: Feng Rongquan <kirifeng@example.com>
Project-URL: Homepage, https://github.com/BACH-AI-Tools/lunar_mcp_server
Project-URL: Repository, https://github.com/BACH-AI-Tools/lunar_mcp_server
Project-URL: Issues, https://github.com/BACH-AI-Tools/lunar_mcp_server/issues
Keywords: mcp,lunar,chinese-calendar,bazi,fortune
Classifier: Development Status :: 4 - Beta
Classifier: Intended Audience :: Developers
Classifier: License :: OSI Approved :: MIT License
Classifier: Programming Language :: Python :: 3
Classifier: Programming Language :: Python :: 3.12
Requires-Python: >=3.12
License-File: LICENSE
Requires-Dist: lunar-python>=1.3.0
Requires-Dist: mcp[cli]>=1.9.0
Requires-Dist: pydantic>=2.0.0
Provides-Extra: dev
Requires-Dist: pytest>=7.0.0; extra == "dev"
Requires-Dist: pytest-asyncio>=0.21.0; extra == "dev"
Requires-Dist: black>=23.0.0; extra == "dev"
Requires-Dist: isort>=5.0.0; extra == "dev"
Requires-Dist: mypy>=1.0.0; extra == "dev"
Dynamic: license-file
